panediv/__init__.py
panediv/exceptions.py
panediv/export.py
panediv/lex.py
panediv/pane.py
panediv/panediv.py
panediv/parse.py
panediv/parsetab.py
panediv/pdc.py
panediv/pdv.py
panediv_nfw-0.1.2.dist-info/LICENSE
panediv_nfw-0.1.2.dist-info/METADATA
panediv_nfw-0.1.2.dist-info/WHEEL
panediv_nfw-0.1.2.dist-info/entry_points.txt
panediv_nfw-0.1.2.dist-info/top_level.txt
panediv_nfw-0.1.2.dist-info/RECORD
