Metadata-Version: 2.1
Name: panediv-nfw
Version: 0.1.2
Summary: Genelate layout template for tmuxinator.
Home-page: https://github.com/nfwprod/panediv-nfw
Author: nfwprod@gmail.com
License: MIT
Platform: UNKNOWN
Classifier: Development Status :: 3 - Alpha
Classifier: Intended Audience :: Developers
Classifier: License :: OSI Approved :: MIT License
Classifier: Operating System :: POSIX :: Linux
Requires-Dist: ply (>=3.11)
